django_slack_processor-0.1.9.dist-info/licenses/LICENSE
slackbot/__init__.py
slackbot/admin.py
slackbot/apps.py
slackbot/base.py
slackbot/models.py
slackbot/management/__init__.py
slackbot/management/commands/__init__.py
slackbot/management/commands/resync_slack.py
slackbot/management/commands/resync_slack_messages.py
slackbot/management/commands/run_bot.py
slackbot/migrations/0001_initial_20210729.py
slackbot/migrations/0002_delete_analyticsbot.py
slackbot/migrations/0003_auto_20210915_1137.py
slackbot/migrations/0004_slack_messages.py
slackbot/migrations/__init__.py
django_slack_processor-0.1.9.dist-info/METADATA
django_slack_processor-0.1.9.dist-info/WHEEL
django_slack_processor-0.1.9.dist-info/top_level.txt
django_slack_processor-0.1.9.dist-info/RECORD
