Metadata-Version: 2.4
Name: django-slack-processor
Version: 0.1.9
Summary: Django app to manage a slack bot with support for custom message processors
Home-page: https://github.com/surface-security/django-slack-processor
Author: PPB - InfoSec Engineering
Author-email: surface@paddypowerbetfair.com
License: MIT
Classifier: Development Status :: 5 - Production/Stable
Classifier: Framework :: Django
Classifier: License :: OSI Approved :: MIT License
Classifier: Intended Audience :: Developers
Classifier: Operating System :: OS Independent
Classifier: Programming Language :: Python
Classifier: Programming Language :: Python :: 3.9
Classifier: Environment :: Web Environment
Classifier: Topic :: Software Development
Requires-Python: >=3.9
License-File: LICENSE
Requires-Dist: Django<6,>=4.2
Requires-Dist: slack-sdk==3.19.2
Requires-Dist: django-logbasecommand<1
Dynamic: license-file
